aio_parallel_tools/__init__.py
aio_parallel_tools/aio_actor/__init__.py
aio_parallel_tools/aio_actor/actor_abc.py
aio_parallel_tools/aio_actor/actor_basic.py
aio_parallel_tools/aio_actor/actor_manager.py
aio_parallel_tools/aio_actor/exception_and_warning.py
aio_parallel_tools/aio_actor/signal.py
aio_parallel_tools/aio_actor/mixins/__init__.py
aio_parallel_tools/aio_actor/mixins/hooks_mixin.py
aio_parallel_tools/aio_actor/mixins/id_mixin.py
aio_parallel_tools/aio_actor/mixins/inbox_mixin.py
aio_parallel_tools/aio_actor/mixins/loop_mixin.py
aio_parallel_tools/aio_actor/mixins/manage_mixin.py
aio_parallel_tools/aio_actor/mixins/task_mixin.py
aio_parallel_tools/aio_task_pool/__init__.py
aio_parallel_tools/aio_task_pool/aio_autoscale_task_pool_lifo.py
aio_parallel_tools/aio_task_pool/aio_autoscale_task_pool_priority.py
aio_parallel_tools/aio_task_pool/aio_autoscale_task_pool_simple.py
aio_parallel_tools/aio_task_pool/aio_fixed_task_pool_lifo.py
aio_parallel_tools/aio_task_pool/aio_fixed_task_pool_priority.py
aio_parallel_tools/aio_task_pool/aio_fixed_task_pool_simple.py
aio_parallel_tools/aio_task_pool/core/__init__.py
aio_parallel_tools/aio_task_pool/core/exception.py
aio_parallel_tools/aio_task_pool/core/signal.py
aio_parallel_tools/aio_task_pool/core/task.py
aio_parallel_tools/aio_task_pool/core/task_pool_abc.py
aio_parallel_tools/aio_task_pool/core/task_pool_base.py
aio_parallel_tools/aio_task_pool/core/mixins/__init__.py
aio_parallel_tools/aio_task_pool/core/mixins/producer_mixin/__init__.py
aio_parallel_tools/aio_task_pool/core/mixins/producer_mixin/simple_producer_mixin.py
aio_parallel_tools/aio_task_pool/core/mixins/queue_mixin/__init__.py
aio_parallel_tools/aio_task_pool/core/mixins/queue_mixin/lifoq_mixin.py
aio_parallel_tools/aio_task_pool/core/mixins/queue_mixin/priorityq_mixin.py
aio_parallel_tools/aio_task_pool/core/mixins/queue_mixin/simpleq_mixin.py
aio_parallel_tools/aio_task_pool/core/mixins/worker_manager_mixin/__init__.py
aio_parallel_tools-0.0.1.dist-info/LICENSE
aio_parallel_tools-0.0.1.dist-info/METADATA
aio_parallel_tools-0.0.1.dist-info/WHEEL
aio_parallel_tools-0.0.1.dist-info/top_level.txt
aio_parallel_tools-0.0.1.dist-info/RECORD
