Metadata-Version: 2.1
Name: aio-parallel-tools
Version: 0.0.1
Summary: simple tools
Home-page: https://python-tools.github.io/aio_parallel_tools/
Author: huangsizhe
Author-email: hsz1273327@gmail.com
License: MIT
Keywords: tools,asyncio
Platform: UNKNOWN
Classifier: Development Status :: 3 - Alpha
Classifier: Intended Audience :: Developers
Classifier: License :: OSI Approved :: MIT License
Classifier: Programming Language :: Python :: 3.7
Classifier: Programming Language :: Python :: 3.8
Classifier: Topic :: Documentation :: Sphinx
Provides-Extra: dev
Requires-Dist: wheel ; extra == 'dev'
Requires-Dist: pep8 ; extra == 'dev'
Requires-Dist: autopep8 ; extra == 'dev'
Requires-Dist: mypy ; extra == 'dev'
Requires-Dist: pydocstyle ; extra == 'dev'
Requires-Dist: mypy-extensions ; extra == 'dev'
Requires-Dist: coverage ; extra == 'dev'
Requires-Dist: lxml ; extra == 'dev'
Requires-Dist: recommonmark ; extra == 'dev'
